{"camp": "Allied", "root": "r0c0", "data": [[{"country": "Allied", "kind": "Production", "name": "RA3 Allied Construction Yard Icons", "type": "unit"}, {"kind": "unused", "duration": 1, "type": "line"}, {"type": "line", "duration": 10, "kind": "success", "unit": {"country": "Allied", "kind": "Production", "name": "RA3 Power Plant Icons"}}, {"kind": "unused", "duration": 1, "type": "line"}, {"type": "line", "duration": 16, "kind": "success", "unit": {"country": "Allied", "kind": "Production", "name": "RA3 Airbase Icons"}}, {"kind": "unused", "duration": 1, "type": "line"}, {"type": "line", "duration": 20, "kind": "success", "unit": {"country": "Allied", "kind": "Production", "name": "RA3 Allied Ore Refinery Icons"}}, {"kind": "unused", "duration": 23, "type": "line"}, {"type": "line", "duration": 10, "kind": "success", "unit": {"country": "Allied", "kind": "Production", "name": "RA3 Power Plant Icons"}}, {"kind": "unused", "duration": 1, "type": "line"}, {"kind": "move", "duration": 26, "type": "line"}, {"kind": "unused", "duration": 1, "type": "line"}, {"type": "line", "duration": 12, "kind": "success", "unit": {"country": "Allied", "kind": "Production", "name": "RA3 Boot Camp Icons"}}, {"type": "line", "duration": 22, "kind": "success", "unit": {"country": "Allied", "kind": "Production", "name": "RA3 Allied Ore Refinery Icons"}}, {"kind": "unused", "duration": 1, "type": "line"}, {"type": "line", "duration": 20, "kind": "success", "unit": {"country": "Allied", "kind": "Production", "name": "RA3 Power Plant Icons"}}, {"type": "line", "duration": 30, "kind": "success", "unit": {"country": "Allied", "kind": "Production", "name": "RA3 Seaport Icons"}}, {"kind": "unused", "duration": 1, "type": "line"}, {"type": "line", "duration": 15, "kind": "success", "unit": {"country": "Allied", "kind": "Production", "name": "RA3_Heightened_Clearance_Icons"}}, {"kind": "unused", "duration": 91, "type": "line"}, {"type": "line", "duration": 26, "kind": "success", "unit": {"country": "Allied", "kind": "Production", "name": "RA3 Armor Facility Icons"}}, {"kind": "unused", "duration": 129, "type": "line"}, {"type": "line", "duration": 24, "kind": "success", "unit": {"country": "Allied", "kind": "Production", "name": "RA3 Power Plant Icons"}}, {"kind": "unused", "duration": 21, "type": "line"}, {"type": "line", "duration": -1, "kind": "success", "unit": {"country": "Allied", "kind": "Production", "name": "RA3 Power Plant Icons"}}], [null, null, null, null, {"type": "unit", "row_prev": 0, "country": "Allied", "kind": "Production", "name": "RA3 Airbase Icons"}, {"kind": "unused", "duration": 3, "type": "line"}, {"type": "line", "duration": 15, "kind": "success", "unit": {"country": "Allied", "kind": "Aircraft", "name": "RA3 Vindicator Icons"}}, {"type": "line", "duration": 15, "kind": "success", "unit": {"country": "Allied", "kind": "Aircraft", "name": "RA3 Vindicator Icons"}}, {"kind": "unused", "duration": 87, "type": "line"}, {"type": "line", "duration": 15, "kind": "success", "unit": {"country": "Allied", "kind": "Aircraft", "name": "RA3 Vindicator Icons"}}, {"kind": "unused", "duration": 103, "type": "line"}, {"type": "line", "duration": 15, "kind": "success", "unit": {"country": "Allied", "kind": "Aircraft", "name": "RA3 Vindicator Icons"}}, {"type": "line", "duration": 15, "kind": "success", "unit": {"country": "Allied", "kind": "Aircraft", "name": "RA3 Vindicator Icons"}}, {"type": "line", "duration": 15, "kind": "success", "unit": {"country": "Allied", "kind": "Aircraft", "name": "RA3 Vindicator Icons"}}, {"type": "line", "duration": 15, "kind": "success", "unit": {"country": "Allied", "kind": "Aircraft", "name": "RA3 Vindicator Icons"}}, {"type": "line", "duration": 15, "kind": "success", "unit": {"country": "Allied", "kind": "Aircraft", "name": "RA3 Vindicator Icons"}}, {"type": "line", "duration": 15, "kind": "success", "unit": {"country": "Allied", "kind": "Aircraft", "name": "RA3 Vindicator Icons"}}, {"type": "line", "duration": 15, "kind": "success", "unit": {"country": "Allied", "kind": "Aircraft", "name": "RA3 Vindicator Icons"}}, {"type": "line", "duration": 15, "kind": "success", "unit": {"country": "Allied", "kind": "Aircraft", "name": "RA3 Vindicator Icons"}}], [null, null, null, null, null, null, null, null, null, null, null, null, {"type": "unit", "row_prev": 0, "country": "Allied", "kind": "Production", "name": "RA3 Boot Camp Icons"}, {"kind": "unused", "duration": 3, "type": "line"}, {"type": "line", "duration": 2, "kind": "success", "unit": {"country": "Allied", "kind": "Infantry", "name": "RA3 Attack Dog Icons"}}, {"type": "line", "duration": 2, "kind": "success", "unit": {"country": "Allied", "kind": "Infantry", "name": "RA3 Attack Dog Icons"}}, {"type": "line", "duration": 2, "kind": "success", "unit": {"country": "Allied", "kind": "Infantry", "name": "RA3 Attack Dog Icons"}}, {"type": "line", "duration": 2, "kind": "success", "unit": {"country": "Allied", "kind": "Infantry", "name": "RA3 Attack Dog Icons"}}, {"type": "line", "duration": 10, "kind": "success", "unit": {"country": "Allied", "kind": "Infantry", "name": "RA3 Allied Engineer Icons"}}, {"kind": "unused", "duration": 29, "type": "line"}, {"type": "line", "duration": 5, "kind": "success", "unit": {"country": "Allied", "kind": "Infantry", "name": "RA3 Peacekeeper Icons"}}, {"type": "line", "duration": 5, "kind": "success", "unit": {"country": "Allied", "kind": "Infantry", "name": "RA3 Peacekeeper Icons"}}, {"type": "line", "duration": 5, "kind": "success", "unit": {"country": "Allied", "kind": "Infantry", "name": "RA3 Peacekeeper Icons"}}, {"type": "line", "duration": 5, "kind": "success", "unit": {"country": "Allied", "kind": "Infantry", "name": "RA3 Peacekeeper Icons"}}, {"type": "line", "duration": 5, "kind": "success", "unit": {"country": "Allied", "kind": "Infantry", "name": "RA3 Peacekeeper Icons"}}, {"type": "line", "duration": 5, "kind": "success", "unit": {"country": "Allied", "kind": "Infantry", "name": "RA3 Javelin Soldier Icons"}}, {"type": "line", "duration": 5, "kind": "success", "unit": {"country": "Allied", "kind": "Infantry", "name": "RA3 Javelin Soldier Icons"}}, {"type": "line", "duration": 5, "kind": "success", "unit": {"country": "Allied", "kind": "Infantry", "name": "RA3 Javelin Soldier Icons"}}, {"type": "line", "duration": 5, "kind": "success", "unit": {"country": "Allied", "kind": "Infantry", "name": "RA3 Javelin Soldier Icons"}}, {"type": "line", "duration": 5, "kind": "success", "unit": {"country": "Allied", "kind": "Infantry", "name": "RA3 Javelin Soldier Icons"}}], [null, null, null, null, null, null, null, null, null, null, null, null, null, null, null, null, {"type": "unit", "row_prev": 0, "country": "Allied", "kind": "Production", "name": "RA3 Seaport Icons"}, {"kind": "unused", "duration": 3, "type": "line"}, {"type": "line", "duration": 10, "kind": "success", "unit": {"country": "Allied", "kind": "Vessels", "name": "RA3 Dolphin Icons"}}, {"type": "line", "duration": 10, "kind": "success", "unit": {"country": "Allied", "kind": "Vessels", "name": "RA3 Dolphin Icons"}}, {"kind": "unused", "duration": 12, "type": "line"}, {"type": "line", "duration": 20, "kind": "success", "unit": {"country": "Allied", "kind": "Vessels", "name": "RA3 Assault Destroyer Icons"}}, {"kind": "unused", "duration": 51, "type": "line"}, {"type": "line", "duration": 30, "kind": "success", "unit": {"country": "Allied", "kind": "Vessels", "name": "RA3 Aircraft Carrier Icons"}}, {"type": "line", "duration": 10, "kind": "success", "unit": {"country": "Allied", "kind": "Vessels", "name": "RA3 Dolphin Icons"}}, {"kind": "unused", "duration": 58, "type": "line"}, {"type": "line", "duration": 10, "kind": "success", "unit": {"country": "Allied", "kind": "Vessels", "name": "RA3 Hydrofoil Icons"}}, {"type": "line", "duration": 10, "kind": "success", "unit": {"country": "Allied", "kind": "Vessels", "name": "RA3 Hydrofoil Icons"}}, {"kind": "unused", "duration": 17, "type": "line"}, {"type": "line", "duration": 30, "kind": "success", "unit": {"country": "Allied", "kind": "Vessels", "name": "RA3 Aircraft Carrier Icons"}}, {"type": "line", "duration": 30, "kind": "success", "unit": {"country": "Allied", "kind": "Vessels", "name": "RA3 Aircraft Carrier Icons"}}], [null, null, null, null, null, null, null, null, null, null, null, null, null, null, null, null, null, null, null, null, {"type": "unit", "row_prev": 0, "country": "Allied", "kind": "Production", "name": "RA3 Armor Facility Icons"}, {"kind": "unused", "duration": 3, "type": "line"}, {"type": "line", "duration": 15, "kind": "success", "unit": {"country": "Allied", "kind": "Vehicles", "name": "RA3 Mirage Tank Icons"}}, {"type": "line", "duration": 15, "kind": "success", "unit": {"country": "Allied", "kind": "Vehicles", "name": "RA3 Mirage Tank Icons"}}, {"type": "line", "duration": 15, "kind": "success", "unit": {"country": "Allied", "kind": "Vehicles", "name": "RA3 Mirage Tank Icons"}}, {"type": "line", "duration": 15, "kind": "success", "unit": {"country": "Allied", "kind": "Vehicles", "name": "RA3 Mirage Tank Icons"}}, {"type": "line", "duration": 15, "kind": "success", "unit": {"country": "Allied", "kind": "Vehicles", "name": "RA3 Mirage Tank Icons"}}, {"kind": "unused", "duration": 33, "type": "line"}, {"type": "line", "duration": 8, "kind": "success", "unit": {"country": "Allied", "kind": "Vehicles", "name": "RA3 Multigunner IFV Icons"}}, {"type": "line", "duration": 8, "kind": "success", "unit": {"country": "Allied", "kind": "Vehicles", "name": "RA3 Multigunner IFV Icons"}}, {"kind": "unused", "duration": 14, "type": "line"}, {"type": "line", "duration": 15, "kind": "success", "unit": {"country": "Allied", "kind": "Vehicles", "name": "RA3 Mirage Tank Icons"}}, {"type": "line", "duration": 15, "kind": "success", "unit": {"country": "Allied", "kind": "Vehicles", "name": "RA3 Mirage Tank Icons"}}, {"type": "line", "duration": 15, "kind": "success", "unit": {"country": "Allied", "kind": "Vehicles", "name": "RA3 Mirage Tank Icons"}}, {"type": "line", "duration": 15, "kind": "success", "unit": {"country": "Allied", "kind": "Vehicles", "name": "RA3 Mirage Tank Icons"}}, {"type": "line", "duration": 15, "kind": "success", "unit": {"country": "Allied", "kind": "Vehicles", "name": "RA3 Mirage Tank Icons"}}, {"type": "line", "duration": 15, "kind": "success", "unit": {"country": "Allied", "kind": "Vehicles", "name": "RA3 Mirage Tank Icons"}}, {"type": "line", "duration": 15, "kind": "success", "unit": {"country": "Allied", "kind": "Vehicles", "name": "RA3 Mirage Tank Icons"}}, {"type": "line", "duration": 15, "kind": "success", "unit": {"country": "Allied", "kind": "Vehicles", "name": "RA3 Mirage Tank Icons"}}, {"type": "line", "duration": 15, "kind": "success", "unit": {"country": "Allied", "kind": "Vehicles", "name": "RA3 Mirage Tank Icons"}}, {"type": "line", "duration": 15, "kind": "success", "unit": {"country": "Allied", "kind": "Vehicles", "name": "RA3 Mirage Tank Icons"}}]]}