{"camp": "Soviet", "root": "r0c0", "data": [[{"country": "Soviet", "kind": "Production", "name": "RA3 Soviet Construction Yard Icons", "type": "unit"}, {"kind": "unused", "duration": 2, "type": "line"}, {"type": "line", "duration": 10, "kind": "success", "unit": {"country": "Soviet", "kind": "Production", "name": "RA3 Barracks Icons"}}, {"kind": "unused", "duration": 2, "type": "line"}, {"type": "line", "duration": 10, "kind": "success", "unit": {"country": "Soviet", "kind": "Production", "name": "RA3 Reactor Icons"}}, {"type": "line", "duration": 20, "kind": "success", "unit": {"country": "Soviet", "kind": "Production", "name": "RA3 Soviet Ore Refinery Icons"}}, {"kind": "unused", "duration": 2, "type": "line"}, {"type": "line", "duration": 20, "kind": "success", "unit": {"country": "Soviet", "kind": "Production", "name": "RA3 Naval Yard Icons"}}, {"kind": "unused", "duration": 1, "type": "line"}, {"type": "line", "duration": 20, "kind": "success", "unit": {"country": "Soviet", "kind": "Production", "name": "RA3 Soviet Ore Refinery Icons"}}, {"kind": "unused", "duration": 2, "type": "line"}, {"type": "line", "duration": 10, "kind": "success", "unit": {"country": "Soviet", "kind": "Production", "name": "RA3 Reactor Icons"}}, {"kind": "unused", "duration": 8, "type": "line"}, {"type": "line", "duration": 20, "kind": "success", "unit": {"country": "Soviet", "kind": "Production", "name": "RA3 Soviet Ore Refinery Icons"}}, {"kind": "unused", "duration": 22, "type": "line"}, {"type": "line", "duration": 30, "kind": "success", "unit": {"country": "Soviet", "kind": "Production", "name": "RA3 Super Reactor Icons"}}, {"kind": "unused", "duration": 19, "type": "line"}, {"type": "line", "duration": 20, "kind": "success", "unit": {"country": "Soviet", "kind": "Production", "name": "RA3 War Factory Icons"}}, {"kind": "unused", "duration": 12, "type": "line"}, {"kind": "move", "duration": 54, "type": "line"}, {"kind": "unused", "duration": 3, "type": "line"}, {"type": "line", "duration": 20, "kind": "success", "unit": {"country": "Soviet", "kind": "Production", "name": "RA3 Soviet Ore Refinery Icons"}}, {"kind": "unused", "duration": 29, "type": "line"}, {"type": "line", "duration": 30, "kind": "success", "unit": {"country": "Soviet", "kind": "Production", "name": "RA3 Airfield Icons"}}, {"kind": "unused", "duration": 27, "type": "line"}, {"kind": "move", "duration": 120, "type": "line"}, {"kind": "unused", "duration": 12, "type": "line"}, {"type": "line", "duration": 20, "kind": "success", "unit": {"country": "Soviet", "kind": "Production", "name": "RA3 Naval Yard Icons"}}], [null, null, {"type": "unit", "row_prev": 0, "country": "Soviet", "kind": "Production", "name": "RA3 Barracks Icons"}, {"kind": "unused", "duration": 1, "type": "line"}, {"type": "line", "duration": 10, "kind": "success", "unit": {"country": "Soviet", "kind": "Infantry", "name": "RA3 Combat Engineer Icons"}}, {"type": "line", "duration": 2, "kind": "success", "unit": {"country": "Soviet", "kind": "Infantry", "name": "RA3 War Bear Icons"}}, {"type": "line", "duration": 2, "kind": "success", "unit": {"country": "Soviet", "kind": "Infantry", "name": "RA3 War Bear Icons"}}, {"kind": "unused", "duration": 2, "type": "line"}, {"type": "line", "duration": 2, "kind": "success", "unit": {"country": "Soviet", "kind": "Infantry", "name": "RA3 War Bear Icons"}}, {"type": "line", "duration": 2, "kind": "success", "unit": {"country": "Soviet", "kind": "Infantry", "name": "RA3 War Bear Icons"}}, {"type": "line", "duration": 2, "kind": "success", "unit": {"country": "Soviet", "kind": "Infantry", "name": "RA3 War Bear Icons"}}, {"kind": "unused", "duration": 75, "type": "line"}, {"type": "line", "duration": 4, "kind": "success", "unit": {"country": "Soviet", "kind": "Infantry", "name": "RA3 Conscript Icons"}}, {"type": "line", "duration": 4, "kind": "success", "unit": {"country": "Soviet", "kind": "Infantry", "name": "RA3 Conscript Icons"}}, {"type": "line", "duration": 4, "kind": "success", "unit": {"country": "Soviet", "kind": "Infantry", "name": "RA3 Conscript Icons"}}, {"type": "line", "duration": 4, "kind": "success", "unit": {"country": "Soviet", "kind": "Infantry", "name": "RA3 Conscript Icons"}}, {"type": "line", "duration": 4, "kind": "success", "unit": {"country": "Soviet", "kind": "Infantry", "name": "RA3 Conscript Icons"}}, {"type": "line", "duration": 4, "kind": "success", "unit": {"country": "Soviet", "kind": "Infantry", "name": "RA3 Conscript Icons"}}, {"type": "line", "duration": 4, "kind": "success", "unit": {"country": "Soviet", "kind": "Infantry", "name": "RA3 Conscript Icons"}}, {"type": "line", "duration": 4, "kind": "success", "unit": {"country": "Soviet", "kind": "Infantry", "name": "RA3 Conscript Icons"}}, {"type": "line", "duration": 4, "kind": "success", "unit": {"country": "Soviet", "kind": "Infantry", "name": "RA3 Conscript Icons"}}, {"type": "line", "duration": 4, "kind": "success", "unit": {"country": "Soviet", "kind": "Infantry", "name": "RA3 Conscript Icons"}}, {"type": "line", "duration": 4, "kind": "success", "unit": {"country": "Soviet", "kind": "Infantry", "name": "RA3 Conscript Icons"}}, {"type": "line", "duration": 4, "kind": "success", "unit": {"country": "Soviet", "kind": "Infantry", "name": "RA3 Conscript Icons"}}, {"type": "line", "duration": 4, "kind": "success", "unit": {"country": "Soviet", "kind": "Infantry", "name": "RA3 Conscript Icons"}}, {"type": "line", "duration": 4, "kind": "success", "unit": {"country": "Soviet", "kind": "Infantry", "name": "RA3 Conscript Icons"}}, {"type": "line", "duration": 4, "kind": "success", "unit": {"country": "Soviet", "kind": "Infantry", "name": "RA3 Conscript Icons"}}, {"kind": "unused", "duration": 183, "type": "line"}, {"type": "line", "duration": 2, "kind": "success", "unit": {"country": "Soviet", "kind": "Infantry", "name": "RA3 War Bear Icons"}}, {"type": "line", "duration": 2, "kind": "success", "unit": {"country": "Soviet", "kind": "Infantry", "name": "RA3 War Bear Icons"}}, {"type": "line", "duration": 2, "kind": "success", "unit": {"country": "Soviet", "kind": "Infantry", "name": "RA3 War Bear Icons"}}], [null, null, null, null, null, null, null, {"type": "unit", "row_prev": 0, "country": "Soviet", "kind": "Production", "name": "RA3 Naval Yard Icons"}, {"type": "line", "duration": 20, "kind": "success", "unit": {"country": "Soviet", "kind": "Vessels", "name": "RA3 Bullfrog (NavYd) Icons"}}, {"type": "line", "duration": 20, "kind": "success", "unit": {"country": "Soviet", "kind": "Vessels", "name": "RA3 Bullfrog (NavYd) Icons"}}, {"type": "line", "duration": 20, "kind": "success", "unit": {"country": "Soviet", "kind": "Vessels", "name": "RA3 Bullfrog (NavYd) Icons"}}, {"type": "line", "duration": 20, "kind": "success", "unit": {"country": "Soviet", "kind": "Vessels", "name": "RA3 Bullfrog (NavYd) Icons"}}, {"kind": "unused", "duration": 60, "type": "line"}, {"type": "line", "duration": 20, "kind": "success", "unit": {"country": "Soviet", "kind": "Vessels", "name": "RA3 Bullfrog (NavYd) Icons"}}, {"kind": "unused", "duration": 24, "type": "line"}, {"type": "line", "duration": 10, "kind": "success", "unit": {"country": "Soviet", "kind": "Vessels", "name": "RA3 Stingray Icons"}}], [null, null, null, null, null, null, null, null, null, null, null, null, null, null, null, null, null, {"type": "unit", "row_prev": 0, "country": "Soviet", "kind": "Production", "name": "RA3 War Factory Icons"}, {"kind": "unused", "duration": 1, "type": "line"}, {"type": "line", "duration": 10, "kind": "success", "unit": {"country": "Soviet", "kind": "Vehicles", "name": "RA3 Hammer Tank Icons"}}, {"type": "line", "duration": 10, "kind": "success", "unit": {"country": "Soviet", "kind": "Vehicles", "name": "RA3 Hammer Tank Icons"}}, {"type": "line", "duration": 10, "kind": "success", "unit": {"country": "Soviet", "kind": "Vehicles", "name": "RA3 Hammer Tank Icons"}}, {"type": "line", "duration": 10, "kind": "success", "unit": {"country": "Soviet", "kind": "Vehicles", "name": "RA3 Hammer Tank Icons"}}, {"type": "line", "duration": 10, "kind": "success", "unit": {"country": "Soviet", "kind": "Vehicles", "name": "RA3 Hammer Tank Icons"}}, {"type": "line", "duration": 10, "kind": "success", "unit": {"country": "Soviet", "kind": "Vehicles", "name": "RA3 Hammer Tank Icons"}}, {"type": "line", "duration": 10, "kind": "success", "unit": {"country": "Soviet", "kind": "Vehicles", "name": "RA3 Hammer Tank Icons"}}, {"type": "line", "duration": 10, "kind": "success", "unit": {"country": "Soviet", "kind": "Vehicles", "name": "RA3 Hammer Tank Icons"}}, {"type": "line", "duration": 10, "kind": "success", "unit": {"country": "Soviet", "kind": "Vehicles", "name": "RA3 Hammer Tank Icons"}}, {"type": "line", "duration": 10, "kind": "success", "unit": {"country": "Soviet", "kind": "Vehicles", "name": "RA3 Hammer Tank Icons"}}, {"type": "line", "duration": 10, "kind": "success", "unit": {"country": "Soviet", "kind": "Vehicles", "name": "RA3 Hammer Tank Icons"}}, {"type": "line", "duration": 10, "kind": "success", "unit": {"country": "Soviet", "kind": "Vehicles", "name": "RA3 Hammer Tank Icons"}}, {"type": "line", "duration": 10, "kind": "success", "unit": {"country": "Soviet", "kind": "Vehicles", "name": "RA3 Hammer Tank Icons"}}, {"type": "line", "duration": 10, "kind": "success", "unit": {"country": "Soviet", "kind": "Vehicles", "name": "RA3 Hammer Tank Icons"}}, {"type": "line", "duration": 10, "kind": "success", "unit": {"country": "Soviet", "kind": "Vehicles", "name": "RA3 Hammer Tank Icons"}}, {"type": "line", "duration": 10, "kind": "success", "unit": {"country": "Soviet", "kind": "Vehicles", "name": "RA3 Hammer Tank Icons"}}, {"type": "line", "duration": 10, "kind": "success", "unit": {"country": "Soviet", "kind": "Vehicles", "name": "RA3 Hammer Tank Icons"}}, {"type": "line", "duration": 10, "kind": "success", "unit": {"country": "Soviet", "kind": "Vehicles", "name": "RA3 Hammer Tank Icons"}}, {"type": "line", "duration": 10, "kind": "success", "unit": {"country": "Soviet", "kind": "Vehicles", "name": "RA3 Hammer Tank Icons"}}, {"type": "line", "duration": 10, "kind": "success", "unit": {"country": "Soviet", "kind": "Vehicles", "name": "RA3 Hammer Tank Icons"}}, {"type": "line", "duration": 10, "kind": "success", "unit": {"country": "Soviet", "kind": "Vehicles", "name": "RA3 Hammer Tank Icons"}}, {"type": "line", "duration": 10, "kind": "success", "unit": {"country": "Soviet", "kind": "Vehicles", "name": "RA3 Hammer Tank Icons"}}, {"type": "line", "duration": 10, "kind": "success", "unit": {"country": "Soviet", "kind": "Vehicles", "name": "RA3 Hammer Tank Icons"}}, {"type": "line", "duration": 10, "kind": "success", "unit": {"country": "Soviet", "kind": "Vehicles", "name": "RA3 Hammer Tank Icons"}}, {"type": "line", "duration": 10, "kind": "success", "unit": {"country": "Soviet", "kind": "Vehicles", "name": "RA3 Hammer Tank Icons"}}, {"type": "line", "duration": 10, "kind": "success", "unit": {"country": "Soviet", "kind": "Vehicles", "name": "RA3 Hammer Tank Icons"}}, {"type": "line", "duration": 10, "kind": "success", "unit": {"country": "Soviet", "kind": "Vehicles", "name": "RA3 Hammer Tank Icons"}}, {"type": "line", "duration": 10, "kind": "success", "unit": {"country": "Soviet", "kind": "Vehicles", "name": "RA3 Hammer Tank Icons"}}, {"type": "line", "duration": 10, "kind": "success", "unit": {"country": "Soviet", "kind": "Vehicles", "name": "RA3 Hammer Tank Icons"}}, {"type": "line", "duration": 10, "kind": "success", "unit": {"country": "Soviet", "kind": "Vehicles", "name": "RA3 Hammer Tank Icons"}}, {"type": "line", "duration": 10, "kind": "success", "unit": {"country": "Soviet", "kind": "Vehicles", "name": "RA3 Hammer Tank Icons"}}, {"type": "line", "duration": 10, "kind": "success", "unit": {"country": "Soviet", "kind": "Vehicles", "name": "RA3 Hammer Tank Icons"}}, {"type": "line", "duration": 10, "kind": "success", "unit": {"country": "Soviet", "kind": "Vehicles", "name": "RA3 Hammer Tank Icons"}}, {"type": "line", "duration": 10, "kind": "success", "unit": {"country": "Soviet", "kind": "Vehicles", "name": "RA3 Hammer Tank Icons"}}, {"type": "line", "duration": 10, "kind": "success", "unit": {"country": "Soviet", "kind": "Vehicles", "name": "RA3 Hammer Tank Icons"}}, {"type": "line", "duration": 10, "kind": "success", "unit": {"country": "Soviet", "kind": "Vehicles", "name": "RA3 Bullfrog Icons"}}, {"type": "line", "duration": 10, "kind": "success", "unit": {"country": "Soviet", "kind": "Vehicles", "name": "RA3 Hammer Tank Icons"}}, {"type": "line", "duration": 10, "kind": "success", "unit": {"country": "Soviet", "kind": "Vehicles", "name": "RA3 Hammer Tank Icons"}}, {"type": "line", "duration": 10, "kind": "success", "unit": {"country": "Soviet", "kind": "Vehicles", "name": "RA3 Hammer Tank Icons"}}, {"type": "line", "duration": 10, "kind": "success", "unit": {"country": "Soviet", "kind": "Vehicles", "name": "RA3 Hammer Tank Icons"}}, {"type": "line", "duration": 10, "kind": "success", "unit": {"country": "Soviet", "kind": "Vehicles", "name": "RA3 Hammer Tank Icons"}}, {"type": "line", "duration": 5, "kind": "success", "unit": {"country": "Soviet", "kind": "Vehicles", "name": "RA3 Terror Drone Icons"}}, {"type": "line", "duration": 10, "kind": "success", "unit": {"country": "Soviet", "kind": "Vehicles", "name": "RA3 Hammer Tank Icons"}}, {"type": "line", "duration": 10, "kind": "success", "unit": {"country": "Soviet", "kind": "Vehicles", "name": "RA3 Hammer Tank Icons"}}, {"type": "line", "duration": 10, "kind": "success", "unit": {"country": "Soviet", "kind": "Vehicles", "name": "RA3 Hammer Tank Icons"}}, {"type": "line", "duration": 10, "kind": "success", "unit": {"country": "Soviet", "kind": "Vehicles", "name": "RA3 Hammer Tank Icons"}}, {"type": "line", "duration": 10, "kind": "success", "unit": {"country": "Soviet", "kind": "Vehicles", "name": "RA3 Hammer Tank Icons"}}, {"type": "line", "duration": 10, "kind": "success", "unit": {"country": "Soviet", "kind": "Vehicles", "name": "RA3 Hammer Tank Icons"}}, {"type": "line", "duration": 10, "kind": "success", "unit": {"country": "Soviet", "kind": "Vehicles", "name": "RA3 Hammer Tank Icons"}}, {"type": "line", "duration": 10, "kind": "success", "unit": {"country": "Soviet", "kind": "Vehicles", "name": "RA3 Hammer Tank Icons"}}, {"type": "line", "duration": 10, "kind": "success", "unit": {"country": "Soviet", "kind": "Vehicles", "name": "RA3 Hammer Tank Icons"}}, {"type": "line", "duration": 10, "kind": "success", "unit": {"country": "Soviet", "kind": "Vehicles", "name": "RA3 Hammer Tank Icons"}}, {"type": "line", "duration": 5, "kind": "success", "unit": {"country": "Soviet", "kind": "Vehicles", "name": "RA3 Terror Drone Icons"}}, {"type": "line", "duration": 5, "kind": "success", "unit": {"country": "Soviet", "kind": "Vehicles", "name": "RA3 Terror Drone Icons"}}, {"type": "line", "duration": 5, "kind": "success", "unit": {"country": "Soviet", "kind": "Vehicles", "name": "RA3 Terror Drone Icons"}}], [null, null, null, null, null, null, null, null, null, null, null, null, null, null, null, null, null, null, null, null, null, null, null, {"type": "unit", "row_prev": 0, "country": "Soviet", "kind": "Production", "name": "RA3 Airfield Icons"}, {"kind": "unused", "duration": 3, "type": "line"}, {"type": "line", "duration": 15, "kind": "success", "unit": {"country": "Soviet", "kind": "Aircraft", "name": "RA3 Twinblade Icons"}}, {"type": "line", "duration": 15, "kind": "success", "unit": {"country": "Soviet", "kind": "Aircraft", "name": "RA3 Twinblade Icons"}}, {"type": "line", "duration": 15, "kind": "success", "unit": {"country": "Soviet", "kind": "Aircraft", "name": "RA3 Twinblade Icons"}}, {"type": "line", "duration": 15, "kind": "success", "unit": {"country": "Soviet", "kind": "Aircraft", "name": "RA3 Twinblade Icons"}}, {"type": "line", "duration": 15, "kind": "success", "unit": {"country": "Soviet", "kind": "Aircraft", "name": "RA3 Twinblade Icons"}}, {"type": "line", "duration": 15, "kind": "success", "unit": {"country": "Soviet", "kind": "Aircraft", "name": "RA3 Twinblade Icons"}}, {"type": "line", "duration": 15, "kind": "success", "unit": {"country": "Soviet", "kind": "Aircraft", "name": "RA3 Twinblade Icons"}}, {"type": "line", "duration": 15, "kind": "success", "unit": {"country": "Soviet", "kind": "Aircraft", "name": "RA3 Twinblade Icons"}}, {"kind": "unused", "duration": 15, "type": "line"}, {"type": "line", "duration": 15, "kind": "success", "unit": {"country": "Soviet", "kind": "Aircraft", "name": "RA3 Twinblade Icons"}}, {"type": "line", "duration": 15, "kind": "success", "unit": {"country": "Soviet", "kind": "Aircraft", "name": "RA3 Twinblade Icons"}}, {"type": "line", "duration": 15, "kind": "success", "unit": {"country": "Soviet", "kind": "Aircraft", "name": "RA3 Twinblade Icons"}}, {"type": "line", "duration": 15, "kind": "success", "unit": {"country": "Soviet", "kind": "Aircraft", "name": "RA3 Twinblade Icons"}}, {"type": "line", "duration": 15, "kind": "success", "unit": {"country": "Soviet", "kind": "Aircraft", "name": "RA3 Twinblade Icons"}}, {"type": "line", "duration": 15, "kind": "success", "unit": {"country": "Soviet", "kind": "Aircraft", "name": "RA3 Twinblade Icons"}}, {"type": "line", "duration": 15, "kind": "success", "unit": {"country": "Soviet", "kind": "Aircraft", "name": "RA3 Twinblade Icons"}}, {"type": "line", "duration": 15, "kind": "success", "unit": {"country": "Soviet", "kind": "Aircraft", "name": "RA3 Twinblade Icons"}}, {"type": "line", "duration": 15, "kind": "success", "unit": {"country": "Soviet", "kind": "Aircraft", "name": "RA3 Twinblade Icons"}}, {"type": "line", "duration": 15, "kind": "success", "unit": {"country": "Soviet", "kind": "Aircraft", "name": "RA3 Twinblade Icons"}}, {"type": "line", "duration": 15, "kind": "success", "unit": {"country": "Soviet", "kind": "Aircraft", "name": "RA3 Twinblade Icons"}}]]}